[{"职责": ["参与互联网软件产品测试的全流程，包括参与需求分析、设计评审，制定测试计划，设计和执行测试用例，进行缺陷跟踪和软件质量分析等；", "制定测试计划，构建测试环境，执行集成测试，回归测试等； ", "保证被测系统的质量，并通过测试流程和方法创新，努力提升研发的质量和效率。"], "职位类别": "技术类", "职位": "SA-腾讯社交广告高级系统测试工程师（研发中心 北京）", "要求": ["工科、计算机或其他相关专业本科以上学历；", "熟悉C/C++/Java等至少一种编程语言,有Shell或Ruby/PHP/Perl/Python等使用经验者优先；", "至少1年以上软件开发、自动化测试工作经验；", "有性能、安全、白盒测试等专业测试领域经验者优先；", "具备互联网广告、搜索、大数据处理、分布式系统、数据库和网络等业务领域测试经验者优先; ", "熟悉Linux或Unix操作系统；", "精通测试流程和测试用例设计方法,能主动进行技术钻研；", "解决复杂问题和编写自动测试工具和系统的能力；", "很强的逻辑思维能力,谈判的能力和冲突管理的能力；", "善于团队合作,理解和适应变化,以结果和行动为准则,努力追求成功。"], "地点": "北京", "招聘人数": "1人"}, {"职责": ["1. 负责腾讯体育多个系统的架构设计与开发；", "2. 调研新技术并与实际业务结合，开发新系统；"], "职位类别": "技术类", "职位": "22086-腾讯体育高级后台开发工程师（北京）", "要求": ["1. 计算机相关专业本科及以上学历", "2. 熟练掌握C、C++、Java、Python、Go 中的一种或多种语言", "3. 参与过大型复杂分布式互联网系统的设计，熟悉常用的互联网技术，包括但不限于RPC、MQ、缓存技术、调用策略等", "4. 熟悉常见的hadoop， hbase， hive， phoenix， ES， kafka， ZK等大数据组件", "5. 有搜索引擎、推荐系统、大数据挖掘等方向有经验优先；善于分析、归纳、解决问题；能够独立或带队进行项目开发；"], "地点": "北京", "招聘人数": "1人"}, {"职责": ["基于SDN控制器平台opendaylight，针对开放光网络开发相关应用； ", "使用java语言，开发光网络网络业务模型，并根据光网络原理对业务进行编排及控制光网络设备；", "研究业界最新技术及其应用，解决创新研发过程中的关键问题和技术难点； ", "根据项目任务计划按时完成软件编码和单元测试工作； ", "按照开发流程编写相应模块的设计文档； ", "与产品经理、测试工程师、其他团队沟通合作，保证产品研发工作的质量和进度； ", "协调或指导团队里其它开发人员的工作；"], "职位类别": "技术类", "职位": "TEG02-光网络控制系统高级研发工程师（北京）", "要求": ["大学本科或以上学历，计算机相关专业； ", "5年以上一种主流后端语言编程经验：Java, 或Scala, 或Python；熟悉SOA和Web Services（REST, SOAP）系统框架；熟悉主流应用服务器（Tomcat, JBoss, Apache, Nginx, 等），3年以上服务器后端开发经验； ", "精通数据库设计和性能优化；熟悉主流RDBMS和NoSQL数据库（MySQL, MongoDB, Memcached, Redis等），以及数据库编程（SQL, JDBC, iBatis, OpenJPA, 等） ", "熟悉常用工程工具：Jenkins, Maven/Git/SVN, Eclipse/IntelliJ等； ", "熟悉设计模式，熟练掌握面向对象编程和事件驱动编程风格； ", "有热情，酷爱技术，有良好的计划、沟通、组织协调能力、语言表达能力；较强的逻辑分析能力和应变能力；良好的团队合作精神；", "熟悉传输系统原理，具备传输系统控制器或网管开发经验优先 ", "有敏捷开发（Agile/Scrum）经验者优先"], "地点": "北京", "招聘人数": "1人"}, {"职责": ["负责手机浏览器FEED流相关推荐算法研发，通过算法优化提升整体推荐的点击率、关注转化率。", "针对消费场景特征，对用户、Item信息进行建模，抽象业务场景，制定有效的召回算法，同时从样本、特征、模型等维度不断优化排序算法。", "紧跟学术界、工业界的前沿技术，结合实际的业务场景进行算法开发、落地，实现团队技术和业务的共同发展。"], "职位类别": "技术类", "职位": "PCG10-QQ浏览器资讯推荐算法高级工程师（北京）", "要求": ["3年及以上推荐/广告/搜索相关的算法经验。", "扎实的机器学习基础，能够运用LR、GBDT、SVM等传统模型解决实际的业务问题，了解深度学习及其在工业界的一些典型应用案例。 ", "熟悉hadoop、hive、storm等常用的大数据处理平台，熟悉python、C++、scala等至少一门编程语言。 ", "较好的沟通能力、团队协作能力，积极主动，愿意接受挑战。"], "地点": "北京", "招聘人数": "1人"}, {"职责": ["利用腾讯平台上大数据的优势，对平台海量语音的各语种的语音进行识别（尤其是国内的小语种），提高系统在海量语音下对数据的分析性能，增强对腾讯各平台信息捕获的辅助支持，为关键词检索性能的进一步提升做服务；主要包括（包括但不限于）：", " 搭建汉语，蒙语，维语和藏语的G2P和大规模语言模型训练（>1T文本量级），搭建基于RNN，LSTM的LM，小语种词典模型的建立和优化工作，小语种声学模型的迁移学习，多任务学习等；", "小语种TTS （维语，藏语，蒙语），包括TTS前端各项NLP技术和vocoder；", "负责针对腾讯全量业务场景的语音识别解码器的优化工作（多语种混合识别，在线识别，并行化，帧速率加速等等）；", "负责跟踪最前沿的声学模型训练技术，配合声学模型训练人员优化模型，搜索空间，改变解码单元；", "提高复杂场景，多语种下语音识别的建模能力和识别速度，性能；", "研究low-resource，zero-speech下建模能力"], "职位类别": "技术类", "职位": "TEG13-小语种语音算法工程师（北京）", "要求": ["硕士或以上学历，信号处理、计算机、电子信息、自动化、模式识别等相关专业;", "3年以上语音识别相关工作经验，扎实的语音信号处理，机器学习，模式识别，深度学习理论功底，对语音识别的训练和解码技术有深入的了解；  ", "会民族语言或小语种G2P，切分，语言模型搭建者优先；", "精通KALDI和至少一个深度学习工具包（Tensorflow, Torch, CNTK）；", "精通 C/C++, 编程能力强；熟悉 Linux 环境开发；熟悉一门脚本语言（Perl, Python, Ruby）", "熟练掌握Shell编程,CUDA编程，多GPU并行计算；", "开发过商用大规模大词汇量连续语音识别系统，或者搭建过语音识别或合成中相应模块者（譬如海量语言模型，解码器，复杂神经网络声学模型）优先；", "参加过zero-speech竞赛，low-resource竞赛，对于NIST DARPA-BABEL项目熟悉者优先；", "在ICASSP, INTERSPEECH, ASRU， CSL, Speech Communication等知名会议和期刊发表过论文者优先；", "良好的沟通能力与团队协作精神"], "地点": "北京", "招聘人数": "1人"}, {"职责": ["利用腾讯平台上大数据的优势，把平台海量非汉语文本翻译成汉语（主要包括维、蒙、藏、朝、哈、彝、壮、粤等小语种到汉语），进而提高对海量非汉语文本的数据分析性能。主要包括：", "机器翻译相关算法的研究，跟踪国际最新算法发展方向和相应技术；", "机器翻译相关算法的开发与性能优化，包括句法分析、语义分析、深度学习等；", "机器翻译语料的挖掘、处理及分析，并可以对其进行领域分类；", "针对模型的不足及难以解决的现象，提出改进建议和方法，提升翻译引擎的性能；", "研究面向多语种、低资源的机器翻译，如无监督学习、半监督学习、迁移学习、zero-shot、low-resource相关研究。"], "职位类别": "技术类", "职位": "TEG13-小语种机器翻译算法工程师 （北京）", "要求": ["机器翻译、自然语言处理相关领域硕士及以上，一年以上工作经验；", "熟悉机器翻译理论，具有相关技术背景或开发经验，熟悉各种机器翻译模型及其参数训练，如SMT、基于RNN的神经机器翻译、基于自注意力机制的神经机器翻译、基于卷积的神经机器翻译等；", "会民族语言或有小语种机器翻译模型搭建者优先；", "具备较好的C/C++或Python开发能力，熟练使用gcc、gdb、Makefile等开发工具，深刻理解并应用各种常用数据结构和算法；", "精通至少一个深度学习工具包（Tensorflow, Theano、PyTorch）；", "熟练掌握Shell编程,CUDA编程，多GPU并行计算；", "参加过CWMT竞赛，WMT竞赛者优先；", "在ACL, EMNLP, IJCAI，AAAI, COLLING, NAACL等知名会议和期刊发表过论文者优先；", "良好的沟通能力与团队协作精神。"], "地点": "北京", "招聘人数": "1人"}, {"职责": ["负责语音识别/合成方向的技术研发工作，包括但不限于语音前端处理、声学模型/语言模型的建立、语言解码、语音合成(TTS)等；", "负责语音识别/合成方向前沿问题的探索与研究；", "结合未来实际应用场景，提供全面的技术解决方案；"], "职位类别": "技术类", "职位": "TEG17-语音识别/合成研究员（北京）", "要求": ["语音识别、机器学习、自然语言处理等领域的计算机科学、电子工程或其它人工智能相关专业博士；", "有语音识别/合成、机器学习、人工智能、计算机视觉、自然语言处理、机器翻译、等领域全球领先企业的工作经验；", "精通至少一种编程语言，包括但不限于Java、C/C++、C#、Python等；", "在计算机科学顶级会议和期刊如NIPS、ICML、Interspeech、ICASSP、ASRU、ACL、EMNLP等发表过论文，有深度学习学术或工程项目经验者优先考虑。"], "地点": "北京", "招聘人数": "1人"}, {"职责": ["负责地图导航诱导引擎的设计和开发；", "负责地图导航诱导引擎对安卓、ios平台支持和调试；", "负责手机地图和车载导航客户端技术规划、业务集成、功能开发、文档撰写、体验改进，配合优化地图位置信息处理和导航技术方向系统结构和算法逻辑优化，以及客户端相关功能模块的适配、升级、体验优化"], "职位类别": "技术类", "职位": "CSIG16-腾讯地图导航引擎开发工程师（北京）", "要求": ["计算机科学、数学、GIS相关专业本科及以上学历；", "地图行业或互联网行业相关工作年限本科3年以上，硕士1年以上；", "两年以上C/C++编程经验，具备良好的代码书写规范；", "熟悉Unix/Linux编程环境和常用脚本语言（Shell/Perl/Python）；", "具有良好的数理基础和严密的逻辑思维能力，能熟练阅读英文文档；", "对安卓和iOS平台有了解，具备一定开发能力。"], "地点": "北京", "招聘人数": "3人"}, {"职责": ["负责腾讯地图搜索策略算法的研发工作，持续迭代提升转化效果和用户体验", "地图场景下用户查询理解，机器学习排序，实时排序模型，深度学习模型", "参与搜索引擎各个底层模块的架构设计、开发工作"], "职位类别": "技术类", "职位": "CSIG16-腾讯地图搜索高级算法工程师 ", "要求": ["计算机相关专业本科以上学历，2年以上工作经验；", "熟悉Linux系统，精通Linux/Unix平台上的C/C 编程，gcc/g /gdb开发环境，精通网络编程、多线程编程；", "熟练掌握常用数据结构及算法，对性能优化有一定的经验;", "掌握Shell、Python等脚本语言更佳。", "具有搜索、自然语言处理、数据挖掘、个性化检索相关领域开发经验优先;", "有地图后台开发经验优先;", "优秀的逻辑思维能力，良好的团队合作精神，较强的沟通能力和学习能力"], "地点": "北京", "招聘人数": "1人"}, {"职责": ["负责腾讯POI搜索服务查询处理模块的研发工作，包括query意图识别、query纠错、query改写等 负责自然语言处理基础工具的研发工作，包括分词、实体识别等 ", "负责腾讯位置POi数据知识图谱搭建"], "职位类别": "技术类", "职位": "CSIG16-腾讯地图自然语言处理工程师 ", "要求": ["2-3年自然语言处理、机器学习等相关工作经验； ", "熟练掌握各种自然语言处理相关的机器学习模型，包括HMM、CRF等；", "有深度学习知识经验优先； ", "熟练掌握C/C++、Python； ", "熟悉hadoop、spark等大数据处理技术优先 ", "积极主动，踏实稳重，团队配合意识强"], "地点": "北京", "招聘人数": "1人"}, {"职责": ["负责腾讯云大数据产品的开发工作。"], "职位类别": "技术类", "职位": "22989-大数据后台开发工程师", "要求": ["计算机、通信等相关专业，本科及以上学历，3年以上大型互联网产品或分布式系统开发设计经验；", " 精通Java, C++, Scala等语言中的一种或几种，并熟悉Shell或Python等一种或几种脚本语言，熟悉Linux/Unix环境；", " 有Hadoop / Spark / Hive / Presto / HBase / Kylin / Impala / Kafka / Flink / Storm/ Redis等使用经验和架构设计、部署经验，熟悉上述常用的分布式系统的原理；", " 有生产环境快速trouble-shooting的经验和能力，擅长分析比较复杂和深层次的原因；", " 热爱大数据和技术，相信技术改变世界，学习能力强，认同数据价值，有面向业务的思维；", " 有OLAP，多维度数据分析经验优先，有对数据仓库有较强的理论基础和理解；", " 具备Spring Cloud等微服务设计和开发经验和能力；", " 有BI系统开发和使用经验以及有DevOps相关实践。"], "地点": "北京", "招聘人数": "1人"}, {"职责": ["负责大数据和AI商业化产品的研发和交付； ", "了解客户需求，按期保质完成研发计划； ", "协助解决方案团队，完成客户化方案的实施； ", "协助运维团队，保障已交付产品的运营和服务。"], "职位类别": "技术类", "职位": "22989-大数据和人工智能高级开发工程师（北京）", "要求": ["本科或以上计算机相关专业；", "精通Linux和C/C++、PHP/Python、Java等一种或几种编程语言； ", "至少5年以上技术开发相关工作经验； ", "熟悉研发管理和质量管理流程，有云计算产品或SaaS服务交付经验； ", "能独立完成模块开发和交付工作； ", "有高并发、大容量后台服务设计经验； ", "熟悉云计算及大数据相关技术； ", "有大数据、机器学习，图片识别、语音识别中至少一种相关背景和经验； ", "有新一代应用设计、开发和运维经验，例如Container、Kubernetes 、DevOps、CD/CI等； ", "具备良好的沟通表能力及团队协作精神、有较强的主动性、责任心与执行能力。"], "地点": "北京", "招聘人数": "1人"}, {"职责": ["1. 开发和维护腾讯云的后台管理 /调度系统（类似于 OpenStack ）", "2. 开发和维护运行在数十万宿主机上的虚拟化 Agent", "3. 开发和维护大规模数据的可视化展现、计算汇总以及预测分析平台", "4. 开发和维护故障迁移/热迁移系统，用于资源腾挪和成本优化"], "职位类别": "技术类", "职位": "22989-云计算后台开发工程师", "要求": ["1. 热情、好学，有钻研和折腾的精神", "2. 有良好的沟通能力和乐于分享的意识", "3. 对云计算领域有浓厚的兴趣", "4. 熟悉 C/C++/Python 中的任意一种，对 Golang/Rust 有所研究的更好", "5. 熟悉 Linux 的基本操作和基本原理，掌握分析、调优工具", "6. 有分布式、虚拟化、 HTTP 服务器开发经验者优先", "7. 有 OpenStack 、 Docker 、 libvirt/QEMU/KVM 等相关开源软件经验者优先"], "地点": "北京", "招聘人数": "1人"}, {"职责": ["1、负责腾讯云 公有云+私有云 中 Kubernetes/Devops产品 关键技术方案设计，参与团队完成核心模块研发工作；", "2、负责 Kubernetes 相关前沿技术规划和调研工作，从技术上保证产品的竞争力；", "3、负责与产品及客户沟通，判定需求的合理性，找出最合适的方式 解决客户问题。"], "职位类别": "技术类", "职位": "22989-腾讯云容器技术专家（北京）", "要求": ["1. 4 年以上后端开发经验，coding、debug 能力强， 有丰富的架构设计经验； ", "2. 熟悉 c/c++/go/java/python/ruby/scala 等至少二种编程语言 ； ", "3. 熟悉 docker/kubernetes/swarm/jenkins/mesos 等至少两种技术；", "4. 熟悉 git/travis/ELK/prometheus 等技术优先； ", "5. 熟悉 aws/google cloud 等云计算厂商产品优先。"], "地点": "北京", "招聘人数": "2人"}, {"职责": ["1、负责负责信息流推荐的后台架构设计、开发和性能调优； ", " 2、建设高效，灵活，易用的平台化推荐引擎和分层实验系统；"], "职位类别": "技术类", "职位": "22090-推荐引擎开发工程师", "要求": ["本科以上学历，计算机相关专业； ", " 熟悉Linux操作系统，精通C++开发语言，至少掌握一门其它语言，如lua，python，php或 go；", " 精通TCP/IP与HTTP等网络协议相关知识，精通网络编程和多线程/多进程开发；", " 1、具备大容量、高性能复杂系统的设计和架构能力；； ", " 2、具有推荐、搜索、广告或存储系统开发经验者优先；", " 3、具备良好的分析解决问题能力，能独立承担任务，有任务进度把控能力； ", " 4、责任心强，自驱力强，主动，好学，具有良好的对外沟通和团队协作能力"], "地点": "北京", "招聘人数": "1人"}, {"职责": ["负责腾讯新闻召回模型优化；", "点击率预估和排序模型优化；", "深度学习相关算法优化和应用。"], "职位类别": "技术类", "职位": "23674-新闻推荐算法高级工程师（北京）", "要求": ["计算机或相关专业本科以上学历，2年以上互联网工作经验；", "熟练掌握C/C++和python语言编程，熟悉linux开发环境，有扎实的数据结构和算法设计功底；", "熟练推荐业务常用理论和算法，在一个或多个领域（如排序模型，召回模型，用户画像，深度学习等）有2年以上实际工作经验；", "有优秀的逻辑思维能力和数据分析能力，善于分析和解决问题；", "良好的沟通能力与团队协作能力；熟练掌握机器学习、深度学习的基础理论和方法，并在自然语言处理任务中有实际应用经验者优先；", "熟练使用一种或几种深度学习框架（如tensorflow、caffe、mxnet、pytorch等），或者熟悉spark、hadoop分布式计算编程者优先。"], "地点": "北京", "招聘人数": "1人"}, {"职责": ["应用多种机器学习技术，解决多源矢量数据融合的业务问题", "通过了解和结合地图道路业务特点，应用多种算法和模型，解决多源数据融合的准确率、召回率、自动化等等问题，提升产品效果"], "职位类别": "技术类", "职位": "CSIG16-道路数据融合算法高级工程师", "要求": ["机器学习相关方向硕士以上学历或 3 年以上工作经验；", "熟悉常见算法和机器学习模型", "熟悉C/C++语言、Python、Java任意一种语言，较强的算法和数据结构功底", "良好的逻辑思维能力，优秀的分析和解决问题的能力，对挑战性问题充满激情", "良好的团队合作精神，较强的沟通能力", "有地图道路数据或者地图行业背景优先"], "地点": "北京", "招聘人数": "1人"}, {"职责": ["负责腾讯地图众包业务核心系统/模块的设计和研发；", "负责关键技术调研和设计实现；", "负责相关系统或模块文档的撰写。"], "职位类别": "技术类", "职位": "CSIG16-地图众包python研发工程师", "要求": ["硕士以上学历，计算机，GIS相关专业优先；", "精通Python、C++等语言，熟悉linux编程环境；", "熟练使用多种脚本语言，熟练使用命令行工具；", "4. 熟悉常用的算法和数据结构；", "熟悉网络编程/多线程编程技术；", "有强烈的上进心和求知欲，善于学习新事物；", "有良好的沟通能力以及较强的分析问题和解决问题的能力；", "地图数据和业务相关背景和工作经验者优先"], "地点": "北京", "招聘人数": "1人"}, {"职责": ["负责地图数据后台的整体功能开发和规划；", "参与系统的需求分析、架构设计、核心框架及组件的编码等开发工作；", "参与相关系统的运营和维护，保证系统稳定可靠运行；", "参与数据库的性能优化和稳定性建设"], "职位类别": "技术类", "职位": "CSIG16-后台开发高级工程师（架构方向）", "要求": ["1. 具备多年的工程和架构开发经验， 自主设计开发过较大规模的网络服务或复杂的业务系统（要求c++或python），对数据库的存储优化、业务模型抽象有较多经验", "2. 对操作系统、网络编程、数据库、常见的分布式系统有较深的技术理解和经验积累", "3.  对Mysql、Kafka、Redis，Hadoop，Spark等分布式存储、队列、计算、集群管理中的一项或多项有深入的理解和实战经验；", "4. 具备较强的业务现状和问题综合理解和分析能力， 能够基于工程、架构、机器学习（optional）等视角和技术去解决问题、优化效果", "5. 具备地图业务数据方向的相关工作经验优先；"], "地点": "北京", "招聘人数": "1人"}, {"职责": ["负责数据库底层研究和特性开发； ", "负责对现有在线系统稳定性优化、性能调优等工作；", "负责云数据库产品的架构优化；", "负责腾讯云平台的数据库后台研发工作；", "负责对现有在线系统稳定性优化、性能调优等工作。"], "职位类别": "技术类", "职位": "22989-腾讯云数据库研发高级工程师(北京/深圳/成都)", "要求": ["5年以上工作经验，计算机相关专业本科以上学历；", "具有kubernetes和docker经验，在容器化和持续集成方面有丰富经验值优先；", "熟悉Linux环境下的 c/c++/go/python/php任一种语言，具有较好的系统分析设计能力；", "熟悉Linux网络编程、熟悉互联网业务开发；", "具备大型分布式系统后台研发经验，具有海量并发开发经验，对Mysql、MongoDB、大数据系统有任一经验者优先；", "积极进取、诚实正直、责任心强，有较好的沟通能力。"], "地点": "北京", "招聘人数": "1人"}, {"职责": ["参与腾讯云云产品数据库的架构设计、交付及服务；", "负责腾讯云数据库的自动化运维和改进，推动提升腾讯云云数据库产品的演进；", "负责与腾讯云大客户针对数据库产品的技术沟通和支持，为大客户提供优质的技术服务；"], "职位类别": "技术类", "职位": "22989-云数据库高级DBA", "要求": ["精通MySQL/SQL Server/Oracle/PostgreSQL/MogonDB/Redis中的一种及以上数据库的运行机制和架构体系，精通数据库架构与设计，对数据库解决方案的优劣和适用场景有深入的理解，能够根据具体场景合理进行数据库选型和架构设计；", "熟悉Linux，熟练掌握Java/Python/Perl/Golang等语言中的一种，可以通过编写程序解决工作中遇到的问题，具备良好的编程风格；", "熟练掌握数据库性能优化技巧，能够定位全链路上的性能瓶颈（网络、CPU、IO、操作系统等），并推动解决问题；", "具有3年以上项目需求分析、方案架构设计工作经验，具有大型行业应用架构经历以及较强的客户需求调研和需求分析能力者优先；", "具备较强的抗压能力，有良好的服务意识；", "良好的团队协作能力，喜欢有挑战的工作；", "良好的沟通表达能力，具备优秀的文档能力，能够熟练编写各类技术文档；"], "地点": "北京", "招聘人数": "1人"}, {"职责": ["负责新闻资讯的搜索算法研发工作，持续提升搜索的相关性和用户体验，具体工作包括(但不限于)：分析海量用户的行为，对用户搜索需求的理解，文本和多模内容的理解，召回和排序算法的设计，机器学习和深度学习模型的研发等。"], "职位类别": "技术类", "职位": "23674-新闻搜索算法高级工程师（北京）", "要求": ["熟练掌握C/C++和python语言编程，熟悉linux开发环境，有扎实的数据结构和算法设计功底；", "在大规模的搜索或推荐系统方面有2年以上的实际项目经验；", "有优秀的逻辑思维能力和数据分析能力，善于分析和解决问题；", "熟练掌握机器学习、深度学习的基础理论和方法，并在自然语言处理（如文本分类、语义理解、知识图谱构建、篇章理解、情感分析、自然语言生成等）或图像视频内容理解（如图像分类或标注、图像质量、视频摘要）上有实际应用经验者优先；", "熟练使用一种或几种深度学习框架（如tensorflow、caffe、mxnet等），或者熟悉spark、hadoop分布式计算编程者优先。"], "地点": "北京", "招聘人数": "1人"}, {"职责": ["1，负责文章的内容理解，包括热点挖掘、兴趣点提取、质量分级、内容画像等"], "职位类别": "技术类", "职位": "23671-企鹅号内容特征算法工程师（北京）", "要求": ["1、计算机或相关专业本科以上学历，2年以上互联网工作经验；", "2、熟练掌握C/C++和python语言编程，熟悉linux开发环境，有扎实的数据结构和算法设计功底；", "3、熟练掌握nlp基础理论和算法，在一个或多个领域（如文本分类、语义理解、知识图谱构建、篇章理解、情感分析、自然语言生成等）有2年以上实际工作经验；", "4、有优秀的逻辑思维能力和数据分析能力，善于分析和解决问题；", "5、良好的沟通能力与团队协作能力；熟练掌握机器学习、深度学习的基础理论和方法，并在自然语言处理任务中有实际应用经验者优先；", "6、熟练使用一种或几种深度学习框架，或者熟悉spark、hadoop分布式计算编程者优先。"], "地点": "北京", "招聘人数": "2人"}, {"职责": ["负责在线服务数据评测系统建设和业务反馈闭环建设", "通过公开途径监测竞品服务和业务、分析提炼和抽取有效信息；通过自身业务数据分析挖掘发现业务潜在方向、用户行为异常特征、系统潜在问题并制定改善方案", "通过用户反馈和行为分析，构建指标体系和数据闭环，改善位置服务和地图导航等业务质量体验"], "职位类别": "技术类", "职位": "CSIG16-腾讯地图服务质量和用户数据分析专家", "要求": ["计算机相关专业本科以上学历，5年以上工作经验", "精通Java或C/C++开发，熟悉python/ shell/ go等脚本和开发语言；熟练掌握数据抓取分析和评测对比方法，熟悉数据挖掘和机器学习、矢量数据处理、空间数据库、分布式计算、hadoop处理环境", "具备良好的用户思维和数据敏感度，能够实现横向竞品对比和纵向同环比分析，分析数据特征发现业务问题", "良好的团队合作精神、主动学习意识、抗压能力"], "地点": "北京", "招聘人数": "1人"}, {"职责": ["负责微信大规模深度学习模型的计算性能优化；", "负责针对微信特定场景的专用深度学习系统的开发与优化；", "负责深度学习系统前沿进展的跟踪，并制定组内的跟进规划。"], "职位类别": "技术类", "职位": "WXG08-113 微信深度学习后台开发工程师（北京）", "要求": ["具备深度学习系统的开发和优化经验；", "具备良好的分析解决问题能力，能合理设计和优化深度学习系统/模块；", "精通C++、python，熟悉高性能计算、CUDA、网络通信等技术；", "具备良好深度学习/机器学习理论和算法基础的优先；", "沟通能力良好，工作认真负责。"], "地点": "北京", "招聘人数": "1人"}, {"职责": ["1、提供相关云产品的售后技术支持，确保客户业务正常运行； ", "2、解决排除用户网络、服务器、存储、数据库等问题及故障；制定相关的技术实施方案，并在实施过程中提供技术支持； ", "3、负责对售后技术事件进行分析和总结，出具技术方案，并推动相关团队解决； ", "4、垂直行业和企业级客户技术支持； ", "5、编写相关产品问题和技术支持分析的报告，整理技术文档； ", "6、根据售后问题能提出建设性意见，并能影响相关部门及时优化。"], "职位类别": "技术类", "职位": "22989-腾讯云售后技术支持（北京）", "要求": ["1、丰富的Linux/Windows系统维护、优化经验，熟悉系统crash的处理方法； ", "2、熟悉TCP/IP协议及有丰富的虚拟网络排错经验； ", "3、熟悉常见数据库（MySQL、SQLServer、PostgreSQL）的排错、调优。 ", "4、熟悉的常见行业的应用架构且有实际经验，如大型电子商务网站架构、多媒体直播平台架构等； ", "5、熟练使用Shell/Perl/Python中一种及以上的脚本语言编程，或熟练使用PHP/Java/ASP中一种及以上的开发语言编程； ", "6、至少有1个熟悉的常见应用软件的使用、优化及排错方法，如Nginx、Apache、Tomcat等； ", "7、熟悉hadoop的生态体系和架构，熟悉MR或Hive的任务优化方法，有Spark的使用和编程经验的更优； ", "8、熟悉对象存储COS，内容分发网络CDN。 ", "9、具有较强的分析问题和快速解决问题的能力，善于学习新技术； ", "10、良好的文档撰写习惯和团队合作意识； ", "11、抗压能力强，有强烈的责任心； ", "12、良好的沟通能力和客户服务意识； ", "13、英语读写或听说流利者优先。"], "地点": "北京", "招聘人数": "2人"}, {"职责": ["1.负责金融相关项目核心算法的开发和实现，并能够指导团队成员完成相关工作。", "2.结合客户需求及金融行业的场景，提供相应的技术解决方案。", "3.协助整个团队完成金融相关系统的搭建与应用。", "4.对机器学习前沿问题进行相关探索与调研。"], "职位类别": "技术类", "职位": "22989-金融算法专家", "要求": ["1.硕士及以上学历，有3年以上金融行业工作经验，对金融行业的业务及理论有着比较深入的了解。", "2.有着扎实的机器学习基础，掌握机器学习模型的开发、上线及后续维护的全过程，如数据处理、模型构建、模型优化等。", "3.熟悉机器学习及统计学的常用算法，例如SVM、LR、MLE、MAP、K-Means、GMM等。", "3.对自然语言处理和深度学习算法有着比较深入的理解，熟悉常用的模型，例如DNN、CNN、RNN、LSTM、Word2Vec、Attention等。", "4.熟悉开源工具，例如TensorFlow、Keras，具备较强的技术集成能力，有分布式开发经验者优先。", "5.编程能力强，熟练掌握Python、C/C++等语言，熟悉Linux开发环境。", "6.性格开朗乐观，善于沟通与分享。"], "地点": "北京", "招聘人数": "1人"}, {"职责": ["负责腾讯云互联网行业PAAS产品研发工作；", "负责腾讯云互联网行业产品架构设计工作；", "负责为互联网客户提供行业云端解决方案、架构优化方案。"], "职位类别": "技术类", "职位": "25663-腾讯云高级后台开发(互联网业务)（北京）", "要求": ["本科以上学历，计算机或相关专业；", "3年以上Linux后台开发经验，精通1门开发语言:C/C++、PHP、Python、Java；", "精通HTTP、TCP/IP协议，网络编程；", "熟悉Linux操作系统原理，常用工具；", "熟悉MySql、开源No-SQL存储及常用开源组件；", "有高并发、大容量后台服务系统设计经验优先；", "云计算或互联网行业架构设计者优先；", "具有良好的学习能力、沟通能力、团队合作意识；", "强烈的责任心与主动性，对所负责工作有owner意识，并能自我驱动成长。"], "地点": "北京", "招聘人数": "1人"}, {"职责": ["腾讯新闻客户端数据仓库和数据计算平台的迭代开发与维护；", "腾讯新闻客户端算法与产品指标的计算和基于指标的洞察分析；", "腾讯新闻内部运营平台的数据开发与维护，指导运营的数据计算与分析。"], "职位类别": "技术类", "职位": "23674-腾讯新闻大数据分析工程师（北京）", "要求": ["计算机相关专业研究生以上学历，3年或以上数据仓库或数据挖掘工作经验；", "熟练掌握Hadoop，Hive，Spark等大数据平台工具，有实际搭建或维护相关平台经验者优先；", "熟练掌握python，scala，Java等编程语言，有大数据分析工作经验者优先；", "较好的逻辑分析能力，良好的沟通交流能力和文字语言表达能力，从事过移动产品数据分析工作者优先。"], "地点": "北京", "招聘人数": "2人"}, {"职责": ["1. 负责腾讯云AI相关产品（图像识别、语音识别、OCR等）的售后技术工作；", "2. 对内部一线部门提供技术支持，解决内部上升的问题；", "3. 与三线研发和产品做好沟通与交流，及时做好复杂问题的上升以及复盘；", "4. 收集、掌握客户需求并编写需求文档，推动产品改进；", "5. 调研、整理相关支出工具的需求与开发，重复机械问题自动化处理；", "6. 组织相关技术培训，对内普及最新产品技术动态以及其他产品信息"], "职位类别": "技术类", "职位": "22989-腾讯云AI产品高级咨询顾问（深圳北京）", "要求": ["1. 统招本科及以上学历，理工科专业背景；", "2. 熟练Linux系统操作", "3. 熟练常用的编程语言（如python、C/C++、Java等），有扎实的编程能力；", "4. 熟练掌握机器学习基本算法，熟悉各种深度神经网络和常用的模型，如CNN, RNN等；", "5. 有图像领域深度学习开发、模式识别、图像处理等经验的优先", "6. 具备较强的沟通协调能力，富有团队合作精神"], "地点": "北京", "招聘人数": "1人"}, {"职责": ["1. 负责腾讯云大数据相关产品的售后技术工作；", "2. 对内部一线部门提供技术支持，解决内部上升的问题；", "3. 与三线研发和产品做好沟通与交流，及时做好复杂问题的上升以及复盘；", "4. 收集、掌握客户需求并编写需求文档，推动产品改进；", "5. 调研、整理相关支出工具的需求与开发，重复机械问题自动化处理；", "6. 组织相关技术培训，对内普及最新产品技术动态以及其他产品信息"], "职位类别": "技术类", "职位": "22989-腾讯云大数据产品高级咨询顾问（深圳北京）", "要求": ["1、熟练Hadoop、Hive、Spark、ES等开源大数据系统的原理和使用；", "2、熟练数据存储系统，数据处理系统，搜索系统的架构，设计，开发，有相关经验者优先；", "3、熟悉Spring技术生态圈Web开发后端框架技术，有实际项目的经验；", "4、熟悉Linux系统，熟练使用shell、Python脚本处理工具；", "5、良好的Java编程能力，熟悉Java开发工具和调试工具；", "6、有良好的产品思维能力，逻辑思维能力及解决问题的能力；", "8、有较强的沟通、协作能力，对数据相关系统感兴趣，富有团队合作精神。"], "地点": "北京", "招聘人数": "1人"}, {"职责": ["负责新闻的文章内容理解，包括但不限于文章主题分类、兴趣点提取、内容摘要、质量分级、情感分析等"], "职位类别": "技术类", "职位": "23674-新闻内容理解高级工程师", "要求": ["1、计算机或相关专业本科以上学历，2年以上互联网工作经验；", "2、熟练掌握C/C++和python语言编程，熟悉linux开发环境，有扎实的数据结构和算法设计功底；", "3、熟练掌握nlp基础理论和算法，在一个或多个领域（如文本分类、语义理解、知识图谱构建、篇章理解、情感分析、自然语言生成等）有2年以上实际工作经验；", "4、有优秀的逻辑思维能力和数据分析能力，善于分析和解决问题；", "5、良好的沟通能力与团队协作能力；熟练掌握机器学习、深度学习的基础理论和方法，并在自然语言处理任务中有实际应用经验者优先；", "6、熟练使用一种或几种深度学习框架（如tensorflow、caffe、mxnet、pytorch等），或者熟悉spark、hadoop分布式计算编程者优先。"], "地点": "北京", "招聘人数": "4人"}, {"职责": ["腾讯新闻客户端相关的数据平台搭建与运行，为产品策略和算法迭代提供基础数据支持。"], "职位类别": "技术类", "职位": "23674-腾讯新闻大数据分析工程师", "要求": ["计算机相关专业研究生以上学历，3年或以上数据仓库或数据挖掘工作经验；熟练掌握Hadoop，Hive，Spark等大数据平台工具，有实际搭建或维护相关平台经验者优先；熟练掌握python，scala，Java等编程语言，有大数据分析工作经验者优先；较好的逻辑分析能力，良好的沟通交流能力和文字语言表达能力，从事过移动产品数据分析工作者优先。"], "地点": "北京", "招聘人数": "2人"}, {"职责": ["负责腾讯新闻/短视频推荐引擎的架构设计、开发和性能调优； ", "结合需求设计实现安全、稳定、高伸缩性、高性能、易用性好的平台化推荐引擎；", "负责推荐数据流程的搭建、监控和优化； ", "负责推荐算法筛选、指标跟踪及性能优化。"], "职位类别": "技术类", "职位": "23674-推荐引擎开发工程师（北京）", "要求": ["本科以上学历，计算机相关专业，3年以上C++后台开发工作经验； ", "熟悉Linux操作系统，精通C++开发语言，至少掌握一门其它语言，如lua，python，php，或 go；", "对海量、高性能、分布式开发有经验者优先； ", "对推荐，搜索，广告系统开发有经验者优先； ", "具备良好的分析解决问题能力，能独立承担任务，有任务进度把控能力；  ", "责任心强，自驱力强，主动，好学，具有良好的对外沟通和团队协作能力。"], "地点": "北京", "招聘人数": "2人"}, {"职责": ["负责PCG业务内容安全平台线系列产品、内容发布系统及相关服务的产品运维，保障服务的稳定，不断提升用户体验；", "建立健全产品运维管理体系和数据体系，实现智能化、自动化运维与快速问题解决；", "针对产品和系统架构的不足，提出改进建议，推动方案执行或负责实施。"], "职位类别": "技术类", "职位": "PCG05-运维工程师（北京）", "要求": ["计算机相关专业本科以上学历，2年以上大型系统运维经验；", "精通各种互联网应用服务：nginx/php/mysql/redis/mongodb/kafka等，熟悉高可用机制，有监控和容灾的实际经验；", "精通shell，具有较好的开发能力，至少熟悉php/golang/python/c其中之一语言；", "熟悉Linux/Unix操作系统原理，熟练应用awk、sed、grep、strace、tcudump、gdb等常用命令；", "具备良好的自学能力,责任心强，有良好的对外沟通和团队协作能力；", "具有开源精神，能阅读源码，有深度学习/大数据平台运维管理经验者优先。"], "地点": "北京", "招聘人数": "1人"}, {"职责": ["负责微信搜索特征工程的建设和优化；", "负责微信搜索中排序算法的研发和优化，包括LTR、点击模型、异构数据排序等；", "负责微信搜索个性化排序和社交行为在搜索中的应用。"], "职位类别": "技术类", "职位": "WXG08-122 微信搜索机器学习算法工程师（北京）", "要求": ["计算机相关专业硕士及以上学历，两年以上的互联网工作经验；", "熟练掌握C/C++，Java，python等编程语言，熟练使用linux环境；", "熟悉常用的自然语言处理、机器学习、数据挖掘算法，并有相关项目经验；", "有搜索、推荐或广告业务的排序质量算法工作经验；", "有分布式机器学习平台构建经验；", "对深度学习、强化学习、迁移学习有深刻的理解和实战应用。"], "地点": "北京", "招聘人数": "1人"}, {"职责": ["负责大数据和人工智能的大数据基础产品的落地实施交付。", "反馈市场信息、客户需求和用户反馈提升产品市场化能力，推动客户诉求的落地。", "和研发团队紧密合作，确保客户项目按时按质完成,协助行业售前架构师提炼和完善解决方案。", "肩负对客户进行大数据产品培训事宜，负责大数据生态合作伙伴的技术支撑和重点客户POC事项。", "建设知识库，工具，流程优化等平台和工具，提升内部服务团队和外部合作伙伴的大数据领域专业度。"], "职位类别": "技术类", "职位": "22989-大数据和人工智能交付架构师（北京/深圳）", "要求": ["对云计算及其大数据相关技术有深刻的理解，", "5年及以上工作经验，2年以上大数据相关项目架构/开发/运维经验，具有大数据平台或应用开发工作经验优先；", "具备良好的沟通能力，能充分理解客户需求并制定解决方案;", "熟练使用大数据处理（Hadoop/Hive/Spark/MapReduce/Kafka/分布式数据库等）相关技术；", "对海量数据传输/存储/计算，数据仓库建设等有丰富经验优先;", "熟悉大数据机器学习框架、数据分析、算法应用相关技术的优先;", "熟悉Linux/Unix系统，精通至少一门编程语言Java/Shell/Python/C++等；", "有激情有进取心，乐于持续学习，抗压性强，良好的服务意识和成就导向。"], "地点": "北京", "招聘人数": "1人"}, {"职责": ["负责快报和短视频在线推荐引擎的开发和优化，保障线上服务质量；", "负责后台基础组件和运营工具的开发工作；", "完成推荐策略以及产品需求的开发。"], "职位类别": "技术类", "职位": "22090-天天快报-高级研发工程师（北京）", "要求": ["计算机相关专业本科以上学历，3年以上开发工作经验；", "精通C/C++，扎实的编码和调试能力；", "熟悉Linux/Unix平台开发，至少熟悉php、shell、python一种脚本语言；", "精通TCP/IP与HTTP等网络协议相关知识，精通网络编程和多线程/多进程开发；", "熟悉Mysql数据库开发，熟悉NoSQL，如memcache/redis；", "具有推荐系统、搜索引擎、广告系统、存储系统开发经验者优先；", "软件知识结构全面，基本功扎实，良好的团队合作能力，善于沟通，热爱开发事业。"], "地点": "北京", "招聘人数": "1人"}, {"职责": ["1、负责天天快报接入和push后台的开发和优化；", "2、负责产品需求分析、模块设计以及软件高质量编码和升级维护。注重系统的日常监控和调优;"], "职位类别": "技术类", "职位": "22090-天天快报-后台开发工程师（北京）", "要求": ["1、3年以上后台开发工作经验；", "2、熟悉Unix/Linux操作系统，精通C++/PHP/GO开发语言，熟悉面向对象开发方法；", "3、精通TCP/IP协议相关知识，精通网络编程，精通HTTP等网络应用协议，精通多线程多进程开发；", "4、熟悉Mysql，Redis等数据库管理、开发，SQL调优；", "5、熟悉Shell/Python等脚本语言；", "6、具备大容量、高性能复杂系统的设计和架构能力；", "7、具有较强的责任心和进取心。"], "地点": "北京", "招聘人数": "1人"}, {"职责": ["1.\t深度分析位置大数据、轨迹大数据及多源海量时空数据，进行数据质量控制、建模和信息提取，解决基于位置服务和商业价值挖掘核心问题。", "2.\t研究开发基于地理大数据、时空数据挖掘及空间优化的创新性应用", "3.\t负责或参与时空大数据分析框架搭建，从事前沿大规模机器学习和知识获取的算法研究与分布式开发", "4.\t跟踪相关领域（工业界及学术界）的最新研究成果"], "职位类别": "技术类", "职位": "CSIG16-地图大数据实验室算法工程师", "要求": ["1.\t计算机、数学、统计学等相关专业硕士以上学位", "2.\t在以下至少一个领域有深入的研究：", "（1）\t统计方法、数据挖掘和机器学习（如深度神经网络、Boosting、图模型、概率统计、最优化方法等）", "（2）\t语义理解检索 (如知识图谱表示、结构化预测、语义解析、信息检索、知识挖掘等）", "（3）\t大数据分析（如搜索/推荐，用户行为分析，位置大数据挖掘等）", "（4）\t计算机视觉（如图像识别理解、人脸检测识别、目标检测和跟踪、OCR、增强现实、图像质量评价、图像分割增强等）", "3.\t良好的编程功底，至少精通C++/JAVA/Python/R/MATLAB至少一门编程语言", "4.\t良好的文献追踪能力，关注相关会议、学术期刊、国际算法竞赛发表的最新技术和专利。"], "地点": "北京", "招聘人数": "1人"}, {"职责": ["为腾讯打造高效、稳定、扩展性较强的LBS数据自动监控、发布系统；", "与团队产品、运营一起发挥创造力，提升数据质量和价值。"], "职位类别": "技术类", "职位": "CSIG16-基础架构工程师（北京）", "要求": ["极好的系统设计和编码能力，重视代码质量，思路清晰，问题导向，行动快速； ", "对Hadoop、Spark、Hive、Kafka、Redis等分布式存储、队列、计算、集群管理中的一项或多项有深入的理解和实战经验；", "较好的沟通能力，能快速理解业务，对数据敏感，并能主导项目的进度，保证团队产出； ", "熟悉Linux开发环境，熟悉C++、Python语言的优先；有LBS相关的系统设计、数据处理经验者优先"], "地点": "北京", "招聘人数": "1人"}, {"职责": ["负责腾讯汽车的质量保证工作，包括版本测试、缺陷跟踪、版本发布、用户反馈等；", "负责腾讯汽车各种类型的测试，包括功能、性能、兼容性等各项质量保证工作；", "参与产品需求评审，设计高质量的用例，对产品研发的进度和质量负责；", "优化测试流程和方法，提升研发效率和质量。"], "职位类别": "技术类", "职位": "PCG04-腾讯汽车测试工程师（北京）", "要求": ["计算机相关专业，本科以上学历；", "移动互联网3年以上测试经验；", "精通测试流程，关注细节体验，具备较强的测试设计能力；", "喜欢钻研业务，能够从发现缺陷中找到成就感；", "掌握至少一门编程语言，包括但不限于python、java、php、golang、c++等；", "优秀的逻辑思维能力，沟通和表达能力；", "较强的责任心、主动性和学习能力。"], "地点": "北京", "招聘人数": "1人"}, {"职责": ["负责腾讯联盟广告系统及算法的开发和优化；", "负责参与广告产品设计和实现，满足不断涌现的产品运营创新需求；", "为流量运营团队设计和提供各类管理优化工具；", "基于海量数据做业务洞察分析。"], "职位类别": "技术类", "职位": "SA-腾讯社交广告联盟广告应用开发高级工程师（北京）", "要求": ["本科及以上学历，计算机相关专业；", "具有扎实的数据结构、算法和编码基础，编码清晰规范，精通C++或java，熟悉Python、Scala；", "具有3年以上后端系统设计和开发经验，有广告系统经验优先；", "熟练掌握各种设计模式和面向对象设计原则，具备较强的模型抽象能力；", "有较强的学习能力和逻辑思维能力，具备良好的问题分析与解决能力；", "有良好的业务思维，对产品运营创新的开发工作有热情；", "善于沟通，工作积极主动，责任心强，具备复杂环境下良好的团队协作能力；", "同时具备Hadoop等大规模分布式开发经验 和/或 终端前端开发经验 优先。"], "地点": "北京", "招聘人数": "1人"}, {"职责": ["测试大规模软件项目（比如微信），并开发测试工具；                                                                         ", "设计具有高度扩展性、可靠性强、与高性能的测试框架；                                                                   ", "优化软件开发周期，提高产品质量，推动内建的产品质量； ", "测试方法/工具的创新。"], "职位类别": "技术类", "职位": "WXG02-116  微信搜索和信息流系统测试工程师（北京）", "要求": ["本科（含）以上学历，成绩优秀； ", "至少精通以下一种语言: C/C++, Java 或 Python； ", "扎实的计算机专业知识，出色的编程能力，以及系统设计能力； ", "对Internet/web相关知识有深入了解，如，Http，Html等； 对测试方法，常用技术，以及web应用有深入且广泛的了解； ", "英语熟练（尤其是读写方面）； ", "具有Unix/Linux相关经验尤佳； ", "具有信息流/推荐/搜索或者人工智能项目相关经验尤佳。"], "地点": "北京", "招聘人数": "1人"}, {"职责": ["深入理解业务，准确分析问题，研发适合的算法与策略，不断优化效果和性能；", "使用机器学习解决实际遇到的问题，比如内容安全中心文本内容分析等；", "负责腾讯网络媒体UGC内容相关的基础研究工作。"], "职位类别": "技术类", "职位": "PCG05-自然语言处理工程师（北京）", "要求": ["计算机（机器学习、自然语言处理等方向）、数学相关专业本科及以上学历； 1-3年自然语言处理、机器学习、数据挖掘、推荐引擎等相关工作经验； 熟练掌握python，c++、linux后台开发； 扎实的数据结构和算法功底； 熟悉Hadoop，spark等优先； 熟悉深度学习，有相关工作经验优先； 积极主动，勇于接受挑战，富有创新精神。"], "地点": "北京", "招聘人数": "2人"}, {"职责": ["深入理解业务，准确分析问题，研发适合的算法与策略，不断优化效果和性能；", "使用机器学习解决实际遇到的问题，比如视频安全拦截。", "负责腾讯业务所覆盖到的媒体视频资源数据的分析和应用研发工作；", "有以下相关项目经验者优先，深度学习图像检测、分类、识别、分割等。"], "职位类别": "技术类", "职位": "PCG05-视觉算法工程师（北京）", "要求": ["优秀的编码与代码控制能力，有扎实的数据结构和算法功底；", "对数据敏感，有优秀的分析&解决问题的能力，对解决具有挑战性问题充满激情；", "熟悉linux开发环境，熟悉C/C++,python,go,perl语言中的一种或多种；", "熟悉大规模数据挖掘、机器学习（深度学习）、分布式计算中一项或多项，并具备实际项目经验者优先；", "学历要求全日制本科及以上。"], "地点": "北京", "招聘人数": "3人"}, {"职责": ["分析自然语言处理在医疗AI行业的应用和需求", "对自然语言类医疗AI提供技术支持，解决技术难题", "考察技术团队开发情况和关键技术环节的质控过程", "提供技术策略支持与学术、交流支持"], "职位类别": "技术类", "职位": "28481-觅影医学NLP研究员", "要求": ["博士及以上学历，熟悉NLP领域的理论基础，掌握统计模型、机器学习相关原理，具有NLP实战经验，参与过相关项目，有医学相关海量数据挖掘、对话管理技术、知识图谱构建、深度学习研发经验者优先；", "熟悉分词，词性标注，实体识别，句法分析，有情感分析，关系抽取和事件抽取经验者优先；", "在NLP相关领域的学术期刊、会议上有学术成果发表优先", "熟悉一些开源的算法库或工具，比如：stanfordNLP、NLTK、Apache OpenNLP、Kaldi、 HTK/HTS、TensorFlow, PyTorch, Hive, Hadoop等，精通Jave, C/C++, Python等至少一门语言"], "地点": "北京", "招聘人数": "1人"}, {"职责": ["腾讯社交广告系统数据工程平台研发，偏重系统架构设计与实现，参加以下一到多项工作： ", "1. 搭建数据仓库，存储并处理海量的实时、批量数据，满足广告业务的定向、分析和模型特征等业务需要", "2. 建设数据发布系统，将数据仓库的数据应用到广告在线业务", "3. 特征工程工程系统建设，为模型方提供特征数据流和特征离线调研、评估平台，并保证模型训练和预测阶段的特征线上与线下一致性；", "4. 用户标识映射、画像数据在线服务的开发与维护；", "5. 广告后台海量日志数据和广告主数据处理平台；", "6. 报表和广告策略的统计数据生成和存储；", "7. 多维透视业务索引和存储；"], "职位类别": "技术类", "职位": "SA-腾讯社交广告大数据研发工程师（北京）", "要求": ["重点大学本科以上学历，计算机相关专业；", "具有扎实的数据结构和算法功底； ", "熟练使用 Java，Scala，C/C++， Python；", "有海量数据处理经验，熟悉 Hadoop，Spark，HBase，Beam等开源框架 ；", "有分布式系统，Tensorflow等机器学习系统等经验优先 ；", "有较强学习能力和逻辑思维能力，具备良好的问题分析与解决能力； ", "善于沟通，工作积极主动，责任心强，具备良好的团队协作能力；"], "地点": "北京", "招聘人数": "1人"}, {"职责": ["负责地图的大数据挖掘工作：应用机器学习/深度学习技术，针对位置、轨迹、内容等海量信息进行数据建模，解决基于基础数据的挖掘等核心问题；跟踪深度学习在工业界以及学术界的最新研究成果。"], "职位类别": "技术类", "职位": "CSIG16-地图大数据挖掘工程师", "要求": ["计算机、数学、统计学、自动化等相关专业等相关专业硕士以上学位；精通数学建模,机器学习及模式识别等领域的理论基础及常用算法，具有良好的逻辑思维能力及数据分析能力，深入理解MapReduce，具有Spark/Hadoop/Storm等大规模分布式计算平台的使用经验；在以下至少一个领域有深入的研究：", "1、统计机器学习（如深度神经网络、Boosting、图模型、概率统计、最优化方法等）；", "2、大数据分析（位置、轨迹内容大数据挖掘，用户行为分析，用户画像等）；", "精通C/C++,熟悉python等一种脚本语言,熟悉linux下开发；有高水平国际期刊和顶级国际会议论文发表者优先。"], "地点": "北京", "招聘人数": "1人"}, {"职责": ["腾讯社交广告系统后台质量研发，偏重算法策略研究、设计与实现， 参与到以下的工作中：", "广告素材(文本和图片)特征挖掘；", "广告精准投放模型和策略的设计与实现；", "广告 A/B Test 实验系统； ", "大规模并行机器学习系统建设。"], "职位类别": "技术类", "职位": "SA-腾讯社交广告推荐算法与系统工程师（北京）", "要求": ["本科及以上学历，硕士、博士优先，2年以上相关工作经验；", "具备扎实的数据结构和算法功底，编码强悍； 熟悉 Linux 开发环境，精通 C/C++，熟悉 Python、Java\\Scala更好；", "具有扎实的数据结构和算法功底； 熟练使用 C/C++ || Python || Java || ；", "有广告、搜索引擎、推荐系统相关技术经验者优先； ", "较强学习能力、逻辑思维能力、具备良好的问题分析与解决能力；", "善于沟通，工作积极主动，责任心强，具备良好的团队协作能力。"], "地点": "北京", "招聘人数": "1人"}, {"职责": ["负责微信看一看在线策略的开发", "负责推荐产品逻辑的实现、实验以及线上效果分析", "负责推荐相关的规则、保量、模型等平台或系统的设计与实现。"], "职位类别": "技术类", "职位": "WXG08-113 微信推荐策略开发工程师（北京）", "要求": ["有1-5年的Linux C/C++ 后台高性能服务器开发经验和数据分析处理经验；", "熟悉python/perl/bash 中的一到多种脚本编程；", "熟练掌握各类常用数据结构和相关算法；", "熟悉分布式系统的设计和应用，熟悉分布式缓存、消息等机制，并能合理应用分布式技术；", "责任感强、有较强的逻辑思维能力、沟通能力；", "有搜索/推荐后台经验优先；"], "地点": "北京", "招聘人数": "1人"}, {"职责": ["使用机器学习、文本挖掘等技术，对微信朋友圈、公众平台文本数据进行分析挖掘；", "基于微信大数据构建吃喝玩乐相关的用户生活画像体系和POI商户画像体系；", "负责用户吃喝玩乐相关搜索查询意图语义分析理解和推荐排序特征的挖掘；"], "职位类别": "技术类", "职位": "WXG01-122 自然语言处理算法工程师（北京）", "要求": ["计算机相关专业，扎实的数据结构和算法功底，精通至少一种编程语言：C、C++、python；", "熟悉常用的NLP、文本挖掘、机器学习算法，有深度学习背景者优先；", "熟悉Linux开发环境，熟悉Hadoop、Spark等大数据计算平台；", "两年以上自然语言处理或数据挖掘相关工作经验，有搜索、推荐项目背景者优先；", "对以上工作内容具有激情，良好的沟通能力，有团队精神；"], "地点": "北京", "招聘人数": "1人"}, {"职责": ["负责腾讯车联网和global车厂（宝马，奔驰等）合作项目的质量管控工作； ", "跟进分析车联网业务的需求、项目进展、外部合作方式，制定相应的测试方案、测试计划、质量目标，并且设计与项目相匹配的测试方法来保证项目质量目标； ", "并且帮助产品从功能,性能,稳定性以及专项质量和效率等方面进行提升； ", "推动研发流程改进，提升产品提测质量；"], "职位类别": "技术类", "职位": "CSIG17-车联网车厂合作项目品质管理工程师（北京）", "要求": ["计算机相关专业本科学历，三年以上软件测试、测试开发、或PM相关经验；精通测试理论和方法； ", "数据分析经验丰富，并且能够根据项目特点制定测试方案、制定项目质量目标，制定测试计划，可以很好的根据项目周期调整来协调资源以保证产品质量的输出； ", "需要有较强的测试团队管理经验； ", "具备良好的沟通能力、协调能力、团队合作能力，定位&深入分析问题能力，强烈的责任心、团队感、积极主动的工作态度；", "英语沟通能力强，最好有外企相关经验；", "有硬件相关项目测试经验,熟悉车厂或车机的质量标准和验收方法,有多方合作测试经验者优先； ", "熟悉java、python开发经验者优先；", "对精益生产以及优化方案有相关经验者优先。"], "地点": "北京", "招聘人数": "1人"}, {"职责": ["主导叮当语音交互平台的闲聊能力建设；", "基于现有业务数据，提升叮当闲聊系统在多领域、多场景下的体验；", "叮当闲聊对话引擎的相关开发，以及新技术和方向的研究；", "与AI Lab的闲聊合作相关的研发工作。"], "职位类别": "技术类", "职位": "CSIG15-叮当闲聊算法研究员", "要求": ["计算机相关专业硕士以上学历，3年以上相关工作经验； ", "扎实的数学基础、机器学习基础、自然语言处理基础； ", "熟练使用C++、Python，有较强的编码能力； ", "工作踏实上进，有良好的团队合作意识。"], "地点": "北京", "招聘人数": "1人"}, {"职责": ["负责知识图谱、NLP/NLU、人机会话相关研发； ", "负责特定场景会话数据分析与挖掘； ", "负责人工智能NLP与行业场景跨界应用探索； ", "负责新技术转化为产品相关研发。"], "职位类别": "技术类", "职位": "22989-云服务开发工程师（NLP方向）（北京）", "要求": ["计算机相关专业硕士以上学历，3年以上工作经验； ", "熟悉知识图谱、NLP/NLU、人机会话等相关算法及实现原理，有相关工作经验或者实验室经验优先； ", "掌握机器学习基本算法并有丰富的实践经验，熟悉caffe或tensorflow优先； ", "熟练掌握C/C++、PHP和Python语言； ", "具备扎实的数学基础，良好的逻辑思维及抗压能力，能够无障碍阅读英文论文。"], "地点": "北京", "招聘人数": "1人"}, {"职责": ["负责微信看一看推荐系统后台系统开发相关工作。"], "职位类别": "技术类", "职位": "WXG08-113 微信推荐后台开发工程师（北京）", "要求": ["有1-5年的Linux C/C++ 后台高性能服务器开发经验和数据分析处理经验；", "熟悉python/perl/bash 中的一到多种脚本编程，对前端cgi开发，css/js 开发有一定认知和经验。", "有推荐系统后台开发经验着优先。"], "地点": "北京", "招聘人数": "1人"}, {"职责": ["负责自动驾驶汽车决策与路径规划算法的研发；", "基于深度学习的驾驶行为建模、模型训练和调优等工作。"], "职位类别": "技术类", "职位": "CSIG16-自动驾驶决策规划（北京）", "要求": ["硕士以上学历，3年以上工作经历，计算机、应用数学、自动化、电子、控制、航空航天、汽车工程等相关专业；", "熟练掌握C和C++编程，熟悉Linux下Shell或Python编程，熟悉CMake，GDB等工具；", " 扎实的数学基础，良好的数学建模能力和英文论文阅读能力；", "有过搜索算法、路径规划、决策树、状态机、图论等相关背景；", "熟悉ROS原理和开发；", "熟练驾驶小型汽车；", "了解深度学习理论，有实际经验优先；", "有实际的无人车开发、驾驶行为决策相关经验。"], "地点": "北京", "招聘人数": "1人"}, {"职责": ["1、负责安全相关业务测试，包括windows端\\Linux端\\MAC端业务的系统测试及专项测试建设；", "2、负责测试方案制定，用例编写及评审，设计或引入测试工具及自动化框架;", "3、推动各类测试技术的研究和落地，提升业务测试质量和效率。"], "职位类别": "技术类", "职位": "CSIG17-系统测试高级工程师", "要求": ["1、计算机相关专业，本科及以上学历，3年以上软件测试经验；", "2、具备扎实的计算机和软件技术基础，良好的测试分析能力，熟悉测试流程及各种测试技巧；", "3、至少掌握一门脚本语言，如: python/perl/shell等，有相关的自动化实战经验；", "4、具备良好的技术钻研能力、沟通能力及团队合作意识；", "  ", "满足下面任意一条或者多条者优先：", "1、掌握一门开发语言, 如:c\\c++\\object-c等；", "2、了解4-7层网络协议 或有渗透测试经验；", "3、有安全产品（杀毒引擎、病毒分析）测试经验者优先。"], "地点": "北京", "招聘人数": "1人"}, {"职责": ["负责虚拟化技术对自动驾驶云服务的支持、调度和性能优化；", "负责AI计算平台在虚拟化系统上的深度优化"], "职位类别": "技术类", "职位": "CSIG16-自动驾驶云平台虚拟化工程师（北京）", "要求": ["精通Unix/Linux操作系统下Java、C/C++或Python服务端编程，有良好的编码习惯，有扎实的计算机理论基础；", "精通kvm/docker等主流虚拟化技术,有Kvm/docker的研发、运营经历;", "有openstack,mesos,kubernetes等开源或自研的大规模集群系统设计、研发经验；", "有linux操作系统、显卡驱动的研发经验者优先；", "深入阅读或优化修改过ROS源码者优先；"], "地点": "北京", "招聘人数": "1人"}, {"职责": ["1. 负责构建公司级内容平台的海量数据分析，挖掘工作；", "2. 跟进内容平台的数据梳理，各数据指标的计算和分析", "3．参与海量数据的存储、查询和运营数据分析体系搭建"], "职位类别": "技术类", "职位": "23671-数据开发工程师（北京）", "要求": ["1. 计算机相关专业，3年及以上相关工作经验,有扎实的计算机理论基础;", "2. 熟悉hadoop、spark、ES等分布式计算和存储平台，研究过Hadoop或者Spark源代码的优先;", "3. 熟悉Java/Python等编程语言，熟练使用SQL，有良好的编码习惯;", "4. 技术视野开阔，有强烈的上进心和求知欲，善于学习和运用新知识；", "5. 善于沟通和逻辑表达，良好的团队合作精神和积极主动的沟通意识；", "6. 具备大数据云平台、计算存储平台、可视化开发平台经验优先；"], "地点": "北京", "招聘人数": "2人"}, {"职责": ["负责腾讯地图后台整体功能开发和规划；", "参与系统的需求分析、架构设计、核心框架及组件的编码等开发工作；", "参与相关系统的运营和维护，保证系统稳定可靠运行。"], "职位类别": "技术类", "职位": "CSIG16-手图高级后台开发工程师（北京）", "要求": ["本科及以上学历，计算机及相关专业；", "3年以上linux/unix 下C、C++开发经验，熟悉一门以上脚本语言（如shell、python等）； ", "精通TCP/IP协议相关知识，精通网络编程，精通HTTP等网络应用协议，精通多线程多进程开发;", "熟悉常用的数据结构和算法，有较强的分析和解决问题的能力，对自己有较高的技术要求；", "工作有激情，具备责任心、良好的沟通技巧和团队合作精神；", "具备良好的问题定位分析能力，有较宽的视野，能快速学习新事物。"], "地点": "北京", "招聘人数": "2人"}, {"职责": ["负责用户兴趣标签的提取挖掘", "负责用户人群挖掘和协同挖掘；", "负责第三方用户行为分析和画像挖掘；", "负责用户行为数据分析及新技术点孵化；", "负责海量用户数据挖掘算法的研究应用。"], "职位类别": "技术类", "职位": "WXG08-122 微信推荐数据挖掘算法工程师（北京）", "要求": ["计算机相关专业硕士及以上学历，两年以上的互联网工作经验；", "熟练掌握C/C++，Java，python等编程语言，熟练使用linux环境；", "熟悉常用的自然语言处理、机器学习、数据挖掘算法，并有相关项目经验；", "参与过搜索引擎、推荐系统、对话系统和广告系统等线上系统者优先；", "参与过知识图谱、排序、点击率预估、语义匹配等模块的优先；", "责任心强，积极主动，勇于接受挑战，具有良好的团队合作和沟通能力。"], "地点": "北京", "招聘人数": "2人"}, {"职责": ["负责腾讯云存储网关、文件存储等存储系统设计、研发、实现；", "发现目前系统的问题，并持续优化。"], "职位类别": "技术类", "职位": "22989-云存储资深研发工程师（北京）", "要求": ["本科及以上学历，计算机相关专业； ", "5年以上Unix、Linux操作系统下开发经验；", "精通C++开发，熟悉其他语言如python、shell、java、php的优先； ", "熟悉常用算法和数据结构，精通网络编程、多线程编程；", "熟悉iscsi、nfs、cifs等协议或有san、nas存储设备开发者优先；", "熟悉ceph、gfs、hdfs等分布式存储系统优先，熟悉ext2、ext3、ext4、xfs等文件系统优先；", "熟悉存储设备、文件系统、 Linux操作系统原理；", "掌握操作系统、设计模式、数据结构、数据库、网络安全等软件知识；", "具备相关分布式大型系统后台研发经验；", "具备相关存储系统项目经验先；", "有云计算或存储行业从业经验；", "具备良好的沟通能力，需求理解能力，团队合作意识。"], "地点": "北京", "招聘人数": "5人"}, {"职责": ["负责腾讯云大数据平台架构的规划和设计；", "参与腾讯云大数据平台和基础产品的开发和改进，保证数据平台的稳定和可靠；", "持续优化云上大数据平台的性能调优，支持海量数据的离线和实时分析，改进多维数据仓库产品的设计与设计，保证在海量数据下，查询结果能高效快速输出；", "关注大数据方向开源产品的技术动态，参与开源产品的技术演进，推动平台产品与技术架构持续更新。"], "职位类别": "技术类", "职位": "22989-腾讯云大数据产品研发专家（北京）", "要求": ["计算机、通信等相关专业，本科及以上学历，8年以上大型互联网产品或分布式系统开发设计经验；", "精通和深度参与Hadoop / Spark / Hive / Presto / HBase / Kylin / Impala / Kafka / Flink / Storm/ Redis等主流大数据产品中至少一项产品的设计与实现，并对多项产品有丰富的使用、部署以及trouble-shooting的经验；", "熟悉和掌握常用的分布式系统的原理，包括在实践中深入理解CAP理论以及BASE设计理念；", "有OLAP，多维度数据分析经验优先，有较丰富的数仓使用经验，对数据仓库有较强的理论基础和理解；", "热爱大数据技术，认同数据价值，思考有深度和体系，对大数据技术发展趋势有自己独到的观点；", "沟通能力强，有较强的技术领导力，能够激励并带领团队完成产品开发上所面临的技术挑战；", "精通Java, C++, Scala等语言中的一种或几种，并熟悉Shell或Python等一种或几种脚本语言，熟悉Linux/Unix环境。"], "地点": "北京", "招聘人数": "3人"}, {"职责": ["参与腾讯云大数据平台架构的规划和设计；", "负责腾讯云大数据平台和基础产品的开发和维护，保证数据平台的稳定和可靠；", "参与云上大数据平台的性能调优，支持海量数据的离线和实时分析，改进多维数据仓库产品的设计与设计，保证在海量数据下，查询结果能高效快速输出；", "关注和参与大数据方向开源产品的技术动态与演进，推动平台产品与技术架构持续更新。"], "职位类别": "技术类", "职位": "22989-腾讯云大数据产品研发工程师（北京）", "要求": ["计算机、通信等相关专业，本科及以上学历，3年以上大型互联网产品或分布式系统开发设计经验；", "精通Java, C++, Scala等语言中的一种或几种，并熟悉Shell或Python等一种或几种脚本语言，熟悉Linux/Unix环境；", "有Hadoop / Spark / Hive / Presto / HBase / Kylin / Impala / Kafka / Flink / Storm/ Redis等使用经验和架构设计、部署经验，熟悉上述常用的分布式系统的原理；", "有生产环境快速trouble-shooting的经验和能力，擅长分析比较复杂和深层次的原因；", "热爱大数据和技术，相信技术改变世界，学习能力强，认同数据价值，有面向业务的思维；", "有OLAP，多维度数据分析经验优先，有对数据仓库有较强的理论基础和理解者优先；", "具备Spring Cloud等微服务设计和开发经验和能力优先；", "有BI系统开发和使用经验以及有DevOps相关实践的优先。"], "地点": "北京", "招聘人数": "6人"}, {"职责": ["1）熟悉工业制造相关业务，并能对工业制造相关的架构组成进行需求分析，同时能针对云计算产品规划出云解决方案，针对云上架构进行优化设计； ", "2）能从网络、服务器、数据中心等不同层面设计传统企业上云的服务架构，能提供IaaS/SaaS/PaaS/DaaS不同层级的解决方案；", "3）确保重点项目的拆解和落地，推进项目实施以及解决方案可复制，推动跨部门合作，推动架构和产品优化；", "4）了解行业技术发展变革方向，能针对云服务特点在行业解决方案上有前瞻性布局。"], "职位类别": "技术类", "职位": "29777-腾讯云工业行业方案架构师（北京/上海/成都）", "要求": ["1）有3年以上服务端开发、运维经验，熟悉Java/Scala/Python/PHP/C/C++至少一种开发语言以及对应开发框架，熟悉高并发处理机制，有海量业务的架构、研发、运维、优化经验；", "2）有成功的传统企业系统的大型应用经验，有面向客户沟通交流、调研需求、宣讲架构的能力，熟悉仿真计算、工业物联网、Mes系统等工业领域相关流程和架构，有过工业制造相关系统建设经验优先；", "3）熟悉Hadoop、Mysql、PostgreSQL、NoSQL、Oracle、Teradata、DB2等数据库中至少一种数据中心建设方案，可以进行产品的独立部署、高可用架构和性能优化，熟悉开源社区解决方案；", "4）熟悉网络架构、虚拟化、分布式存储，深入理解IT基础设施领域，如服务器、网络设备的技术和架构，有IT交付经验优先；", "5）具备团队合作经验，学习能力强，抗压能力强； ", "6）具备良好的文档能力，善于总结沟通，清晰表达技术观点和架构意图，能熟练的编写技术文档；", "7）有一定的项目管理经验，能进行需求管理、期望管理、团队协作管理，有和ISV管理合作经验优先；", "8）有PMP认证优先。"], "地点": "北京", "招聘人数": "1人"}, {"职责": ["负责视频搜索和推荐中的自然语言处理及大规模数据分析的研发；", "负责分词、词性标注、实体识别、视频标签提取、视频分类、查询分析查询意图识别、视频领域知识图谱的构建等相关工作。"], "职位类别": "技术类", "职位": "PCG19-腾讯视频自然语言处理高级工程师（北京）", "要求": ["精通自然语言处理，数据挖掘相关技术3年以上相关工作经验；", "熟悉机器学习和数据挖掘的基本算法，有实际工程研究经验；", "熟悉深度学习技术；", "精通C/C++/python编程，熟悉常用算法及优化；", "具备优秀的分析和解决问题的能力，良好的沟通和学习能力。"], "地点": "北京", "招聘人数": "2人"}, {"职责": ["负责腾讯视频的大数据收集、存储、分析工作；负责从大数据中分析、抽取用户特征、视频特征，并且在推荐、搜索等业务中应用。"], "职位类别": "技术类", "职位": "PCG19-腾讯视频大数据高级工程师（北京）", "要求": ["精通Linux平台下C/C++开发；熟悉Python、Java、Scalar开发；具备Hadoop/Spark等分布式计算平台的使用经验；熟悉分布式存储系统；熟悉网络编程和IO模型；熟练掌握各类常用数据结构和相关算法；责任感强、有较强的逻辑思维能力、沟通能力。有大数据挖掘经验者优先；熟悉Linux平台下C/C++开发优先考虑。"], "地点": "北京", "招聘人数": "1人"}, {"职责": ["负责运营系统、用户画像系统、内容推荐系统、消息推送系统的建设。"], "职位类别": "技术类", "职位": "CSIG16-手图运营开发工程师（北京）", "要求": ["本科及以上学历，计算机及相关专业;", "2年以上linux/unix 下C/C++/Java开发经验，熟悉一门以上脚本语言（如shell、python等）；", "熟悉常用的数据结构和算法，有较强的分析和解决问题的能力，对自己有较高的技术要求;", "工作有激情，具备责任心，良好的沟通技巧和团队合作精神; ", "有高并发后台系统、大规模运营系统设计开发经验者优先; ", "熟悉常见的Web前后台开发技术者优先；", "熟悉数据分析、hadoop、机器学习、数据挖掘方法优先。"], "地点": "北京", "招聘人数": "1人"}, {"职责": ["负责智能对话机器人领域意图识别、语义分析相关算法研究及业务应用落地；", "利用机器学习、数据挖掘技术进行文本挖掘，负责领域行业知识图谱构建及其在对话bot中应用落地。"], "职位类别": "技术类", "职位": "WXG08-121 微信模式识别自然语言处理算法工程师（北京）", "要求": ["研究生及以上学历，计算机相关专业；", "扎实的数据结构和算法功底，精通C/C++，熟悉python、Java等编程语言；", "熟悉分词、词性标注、命名实体识别、文本分类、聚类等常用NLP算法，Deep Learning for NLP研究背景者优先；", "熟悉知识图谱中文本挖掘算法，有Linux开发经验，熟悉Hadoop、Spark等大数据计算平台；", "有搜索引擎、对话系统、语音助手项目研究背景者优先；", "对以上工作内容具有激情，善于沟通，有团队精神。"], "地点": "北京", "招聘人数": "1人"}, {"职责": ["负责阅读推荐质量算法优化；", "负责各类排序模型、特征工程相关工作；", "负责机器学习算法调研和平台建设。"], "职位类别": "技术类", "职位": "WXG08-122 微信推荐机器学习算法工程师（北京）", "要求": ["计算机相关专业硕士及以上学历，两年以上的互联网工作经验；", "熟练掌握C/C++，Java，python等编程语言，熟练使用linux环境；", "熟悉常用的自然语言处理、机器学习、数据挖掘算法，并有相关项目经验；", "有搜索、推荐或广告业务的排序质量算法工作经验；", "有分布式机器学习平台构建经验；", "对深度学习、强化学习、迁移学习有深刻的理解和实战应用。"], "地点": "北京", "招聘人数": "2人"}, {"职责": ["负责自动驾驶视觉感知任务开发；", "支持融合感知、规划控制、地图构建等相关模块研发工作；"], "职位类别": "技术类", "职位": "CSIG16-自动驾驶计算机视觉算法工程师（北京)", "要求": ["熟悉经典机器学习方法，具有丰富的深度学习研究和工程经验；", "在图像识别、目标检测跟踪等相关领域有丰富的研发经历；", "精通C/C++/Python等编程语言，有丰富的Linux开发经验；", "具有较强的算法理解能力，能够快速复现论文结果；", "具备较好的沟通表达能力和团队合作精神。"], "地点": "北京", "招聘人数": "1人"}, {"职责": ["负责自动驾驶云端样本生产与算法评测、高精度地图在线生产管理、场景仿真云、自动驾驶实车云控等多个“大数据业务平台”，后台高性能数据服务框架设计与开发，持续优化升级；", "数据并行计算性能和算法调优；", "提升自动驾驶云平台的影响力和易用性。"], "职位类别": "技术类", "职位": "CSIG16-自动驾驶云平台高级后台开发工程师(北京)", "要求": ["精通Unix/Linux操作系统下Java、C/C++或Python服务端编程，有良好的编码习惯，有扎实的计算机理论基础；", "有两年以上大规模图像点云web绘制或可视化平台开发经验，两年以上ROS系统开发经验，深入阅读或优化修改过ROS源码者优先；", "熟悉ceph/hdfs/S3等分布式存储系统、hbase/mongodb等非结构化数据库，有大规模高并发分布式系统开发经验，有大型网站后台开发经验；", "熟练掌握开源大数据处理技术栈，有Hadoop/spark/storm等框架两年以上实际项目使用经验，深入阅读或修改过源码者优先；", "具备良好的学习能力、分析解决问题能力；", "具有高度的责任心和团队合作精神；", "有3年以上互联网产品后台开发经验者优先；", "有丰富数据库使用经验者优先。"], "地点": "北京", "招聘人数": "1人"}, {"职责": ["熟悉传统行业业务（智慧城市、地产、家电、旅游、汽车等），并能对传统业务架构组成进行需求分析，同时能针对云计算产品规划出云解决方案，针对云上架构进行优化设计；", "能从网络、服务器、数据中心等不同层面设计传统企业上云的服务架构，能提供IaaS/SaaS/PaaS/DaaS不同层级的解决方案；", "确保重点项目的拆解和落地，推进项目实施以及解决方案可复制，推动跨部门合作，推动架构和产品优化；", "了解行业技术发展变革方向，能针对云服务特点在行业解决方案上有前瞻性布局。"], "职位类别": "技术类", "职位": "CSIG02-腾讯云行业方案架构师（北京/上海/深圳/成都/武汉）", "要求": ["本科或以上学历，3年以上服务端开发、运维经验，熟悉Java/Scala/Python/PHP/C/C++至少一种开发语言以及对应开发框架，熟悉高并发处理机制，有海量业务的架构、研发、运维、优化经验；", "有成功的传统企业系统的大型应用经验，有面向客户沟通交流、调研需求、宣讲架构的能力，物联网经验优先；", "熟悉Hadoop、Mysql、PostgreSQL、NoSQL、Oracle、Teradata、DB2等数据库中至少一种数据中心建设方案，可以进行产品的独立部署、高可用架构和性能优化，熟悉开源社区解决方案；", "熟悉网络架构、虚拟化、分布式存储，深入理解IT基础设施领域，如服务器、网络设备的技术和架构，有IT交付经验优先；", "具备团队合作经验，学习能力强，抗压能力强；", "具备良好的文档能力，善于总结沟通，清晰表达技术观点和架构意图，能熟练的编写技术文档；", "有一定的项目管理经验，能进行需求管理、期望管理、团队协作管理，有和ISV管理合作经验优先；", "有PMP认证优先。"], "地点": "北京", "招聘人数": "2人"}, {"职责": ["负责开发证券行情后台系统； ", "参与相关产品需求讨论、架构设计、财经后台现有系统的架构优化，升级；", "跟进后台服务研发运维工作。"], "职位类别": "技术类", "职位": "23486-后台开发高级工程师（北京）", "要求": ["熟悉掌握C/C++/Python/PHP/GO一种或多种开发语言，熟悉shell命令；", "包括2年以上Unix/linux下Server开发经验，熟悉Unix/Linux下常用架构设计方法；", "熟练使用 Mysql、Redis等数据库，具有MySQL索引优化、查询优化和存储优化方面的经验；", "熟练使用Linux操作系统，了解常用的算法，数据结构，掌握面向对象编程； ", "代码风格良好，熟悉常见的设计模式，具备中型系统的规划设计能力，具备运维问题的分析定位能力", "工作积极主动，有责任心，严谨细致，有激情，有一定的测试意识，有一定的项目管理意识；"], "地点": "北京", "招聘人数": "1人"}, {"职责": ["测试大规模软件项目（比如微信），并开发测试工具；", "设计具有高度扩展性、可靠性强、与高性能的测试框架；", "优化软件开发周期，提高产品质量，推动内建的产品质量；", "测试方法/工具的创新；"], "职位类别": "技术类", "职位": "WXG02-116 微信搜索和信息流系统测试程师（北京）", "要求": ["本科（含）以上学历，成绩优秀；", "至少精通以下一种语言: C/C++, Java 或 Python；", "扎实的计算机专业知识，出色的编程能力，以及系统设计能力；", "对Internet/web相关知识有深入了解，如，Http，Html等；", "对测试方法，常用技术，以及web应用有深入且广泛的了解；", "英语熟练（尤其是读写方面）；", "具有Unix/Linux相关经验尤佳；", "具有信息流/推荐/搜索或者人工智能项目相关经验尤佳。"], "地点": "北京", "招聘人数": "1人"}, {"职责": ["负责视觉算法的研发，包括但不限于：图像内容识别、物体检测和跟踪、图像语义分割、文字识别等； 与平台开发人员对接，实现算法植入；移动端算法设计、移植及优化。"], "职位类别": "技术类", "职位": "CSIG16-地图众包计算机视觉高级算法工程师", "要求": ["计算机、自动化、数学等相关专业,硕士及以上学历; 精通数学建模,扎实的模式识别、计算机视觉、图像处理理论基础,掌握领域内常用算法,如视频图像中特征提取、目标检测、跟踪、分类、文字识别算法; 熟悉深度学习CNN,RNN相关理论; 精通一个以上相关开发工具(caffe,tensorflow,torch)的使用,并深刻了解内部机制; 精通cuda、opencl等并行加速方法,熟悉hadoop框架; 精通C/C++,熟悉python等一种脚本语言,熟悉linux下开发。在以下领域有实际项目经验者优先：", "1、熟悉深度学习模型优化和加速算法；", "2、熟悉深度学习嵌入式移植和优化；", "3、熟悉基于深度学习的文字识别算法；", "有在计算机视觉(CVPR,ICCV,ECCV)等相关会议发表论文者优先;"], "地点": "北京", "招聘人数": "1人"}, {"职责": ["1.负责在多种地图形态（拓扑，网格等）下的路径规划算法研发；", "2.负责机器人行为规划、以及基于运动几何单元的运动规划算法研发；", "3.负责基于深度/增强学习方法的行为预测及运动规划算法研发；"], "职位类别": "技术类", "职位": "CSIG16-自动驾驶机器人轨迹规划算法工程师（北京）", "要求": ["1.自动化、机器人、数学、机器学习等相关专业硕士及以上学历，3年以上工作经验；", "2.精通C/C++，熟悉C++11，多线程调度等，熟练掌握Python；", "3.精通常见的路径规划算法：A*、PRM、RRT等，2年以上的实际工作经验；", "4.熟悉轨迹预测算法：MDP、POMDP、了解MCMC，LDA算法；", "5.熟悉深度/增强学习相关算法：RNN、LSTM等，至少掌握一种深度学习框架（TensorFlow，MXNet、PyTorch、Caffe等）、熟悉gym、universe等平台；", "6.具备良好的团队合作和沟通能力，对前沿领域有高度的技术敏感性，勇于接受挑战，且执行力强；", "7.精通ROS开发、熟悉Gazebo、V-Rep等仿真软件，2年以上实际开发经验者优先；参加过机器人领域的相关比赛并取得较好成绩者优先；"], "地点": "北京", "招聘人数": "1人"}, {"职责": ["负责可见光相机、激光雷达、毫米波雷达等多传感器的信息处理和融合，提高自主驾驶车的环境感知能力；", "负责基于多源信息融合的目标检测、跟踪、识别与定位；", "负责基于多源信息融合的环境特征抽取，为地图构建提供支持；", "为基于基于多源信息融合的导航定位提供支持。"], "职位类别": "技术类", "职位": "CSIG16-自动驾驶融合感知(北京)", "要求": ["硕士以上学历,2年以上工作经历,自动化、电子工程、计算机、应用数学、航空航天、测绘遥感、电信和微电子等相关专业;", "熟悉多传感器信息融合算法;", "熟悉传感器(激光、相机、GPS/IMU、雷达等)校准算法,并具有丰富的实践经验;", "精通掌握C/C++,熟悉Linux下Shell或Python编程,熟练掌握CMake,GDB等工具;", "善于分析和解决问题,具备较好的沟通表达能力和团队合作精神;", "有图像处理和模式识别相关经验优先;", "具有自主驾驶系统工程设计经验优先。"], "地点": "北京", "招聘人数": "1人"}, {"职责": ["负责微信模式识别中心对话系统的后台基础平台的构建， 包括程序框架设计与开发、系统性能优化；", "数据索引存储和检索的设计、日志系统及离线数据pipeline搭建。"], "职位类别": "技术类", "职位": "WXG08-113 微信自然语言处理系统后台开发工程师（北京）", "要求": ["3年以上Linux c/c++后台高性能服务器开发经验; ", "具有扎实的数据结构和算法功底；", "具备良好的分析解决问题能力，能合理设计和开发独立模块； ", "熟悉Java/Python; 熟悉Hadoop, Spark等大数据处理框架；", "沟通能力良好，工作认真负责；", "具备一定产品思维，熟悉搜索、推荐系统后台开发经验者优先。"], "地点": "北京", "招聘人数": "2人"}, {"职责": ["负责视频用户行为序列数据挖掘工作，基于海量用户行为序列数据，挖掘行为模式、关键行为路径、用户兴趣等，为视频内容分发以及相关分析提供数据基础"], "职位类别": "技术类", "职位": "PCG19-腾讯视频数据挖掘高级工程师（北京） ", "要求": ["三年以上的自然语言处理、机器学习、数据挖掘相关工作经验；", "具有linux环境编程基础，熟悉c++/java/python/scala等一门以上编程语言 ，有spark/hadoop/storm等大数据平台的开发经验；", "熟悉常用的机器学习、文本分类和聚类算法，如svm，朴素贝叶斯等；", "具备优秀的分析和解决问题的能力，良好的沟通和学习能力。"], "地点": "北京", "招聘人数": "1人"}, {"职责": ["1.搭建基于图像特征/CNN的图像/视频中的文字信息检测模型并优化", "2.搭建基于CNN/LSTM的中文、英文等多语种OCR识别模型并优化", "3.模型压缩及优化，提高算法速度，性能", "4.追踪前沿的文字检测/识别技术并复现，优化"], "职位类别": "技术类", "职位": "TEG13-图像OCR算法工程师(北京)", "要求": ["1.硕士或以上学历，信号处理、计算机、电子信息、自动化、模式识别等相关专业;", "2.2年以上计算机视觉领域相关工作经验，图像检测/识别，视频分析/目标追踪领域有深入的了解；熟悉经典的机器学习、深度学习算法并有实践经验，包括LR、SVM、GBDT、DNN、LSTM等；对算法优化有一定经验，有效提升准确率", "3.精通至少一个主流深度学习工具包（caffe，Tensorflow, mxnet，pyTorch）；", "4.精通 C/C++, 编程能力强；熟悉 Linux 环境开发；熟悉一门脚本语言（Perl, Python, Ruby）", "5.熟练CUDA编程，多GPU并行计算者优先", "6.在国际顶级会议期刊上发表过成果者优先", "7.良好的沟通能力与团队协作精神"], "地点": "北京", "招聘人数": "1人"}]